self_utils/__init__.py
self_utils/ahps.py
self_utils/coast.py
self_utils/metrics.py
self_utils/norms.py
selfutils-0.1.2.dist-info/LICENSE.txt
selfutils-0.1.2.dist-info/METADATA
selfutils-0.1.2.dist-info/WHEEL
selfutils-0.1.2.dist-info/top_level.txt
selfutils-0.1.2.dist-info/RECORD
